docs/doctrees/nbsphinx/notebooks_sample_dss_files_19_0.png
docs/doctrees/nbsphinx/notebooks_sample_dss_files_19_1.png
docs/doctrees/nbsphinx/notebooks_sample_dss_files_21_0.png
docs/doctrees/nbsphinx/notebooks_sample_dss_files_21_1.png
docs/doctrees/nbsphinx/notebooks_sample_dss_files_25_0.png
docs/doctrees/nbsphinx/notebooks_sample_dss_files_25_1.png
docs/doctrees/nbsphinx/notebooks_sample_dss_files_26_0.png
docs/doctrees/nbsphinx/notebooks_sample_dss_files_26_1.png
docs/doctrees/nbsphinx/notebooks_sample_dss_files_36_0.png
docs/doctrees/nbsphinx/notebooks_sample_dss_files_36_1.png
docs/html/_images/notebooks_sample_dss_files_19_0.png
docs/html/_images/notebooks_sample_dss_files_19_1.png
docs/html/_images/notebooks_sample_dss_files_21_0.png
docs/html/_images/notebooks_sample_dss_files_21_1.png
docs/html/_images/notebooks_sample_dss_files_25_0.png
docs/html/_images/notebooks_sample_dss_files_25_1.png
docs/html/_images/notebooks_sample_dss_files_26_0.png
docs/html/_images/notebooks_sample_dss_files_26_1.png
docs/html/_images/notebooks_sample_dss_files_36_0.png
docs/html/_images/notebooks_sample_dss_files_36_1.png
docs/html/_static/file.png
docs/html/_static/minus.png
docs/html/_static/plus.png
docsrc/conf.py
perftest/hec_read_large_file.py
perftest/pydss_read_large_file.py
perftest/read_large_file.py
perftest/vscript_read_large_file.py
pyhecdss/__init__.py
pyhecdss/_pyheclib.cp312-win_amd64.pyd
pyhecdss/_version.py
pyhecdss/core.py
pyhecdss/hecwrapper.c
pyhecdss/pyheclib.i
tests/__init__.py
tests/pytest.ini
tests/test1.dss
tests/test_catalog.dsc
tests/test_catalog_dsc_read.py
tests/test_failing_catalog.dsc
tests/test_helper.py
tests/test_peraver.py
tests/test_pyhecdss.py
tests/test_pyhecdss_intrinsic.py
tests/test_pyheclib.py
tests/test_rts_offset.py
tests/test_twstr.py
pyhecdss-1.5.12.dist-info/AUTHORS.rst
pyhecdss-1.5.12.dist-info/LICENSE
pyhecdss-1.5.12.dist-info/METADATA
pyhecdss-1.5.12.dist-info/WHEEL
pyhecdss-1.5.12.dist-info/top_level.txt
pyhecdss-1.5.12.dist-info/RECORD
