Metadata-Version: 2.1
Name: pyhecdss
Version: 1.5.12
Summary: For reading/writing HEC-DSS files
Author-email: Nicky Sandhu <psandhu@water.ca.gov>
License: MIT
Project-URL: homepage, https://github.com/dwr-psandhu/pyhecdss
Keywords: pyhecdss,hec-dss,hydrology
Classifier: Development Status :: 2 - Pre-Alpha
Classifier: Intended Audience :: Developers
Classifier: License :: OSI Approved :: MIT License
Classifier: Natural Language :: English
Classifier: Programming Language :: Python :: 3
Classifier: Programming Language :: Python :: 3.11
Classifier: Programming Language :: Python :: 3.12
Requires-Python: >=3.11
License-File: LICENSE
License-File: AUTHORS.rst
Requires-Dist: numpy
Requires-Dist: pandas
